boost_headers
