Metadata-Version: 2.4
Name: boost-headers
Version: 1.81.0.post1
Summary: Boost headers.
Requires-Python: >=3.9
License-File: LICENSE
Provides-Extra: dev
Requires-Dist: pytest; extra == "dev"
Dynamic: license-file
